{
  "annotations": {
    "list": [
      {
        "builtIn": 1,
        "datasource": "-- Grafana --",
        "enable": true,
        "hide": true,
        "iconColor": "rgba(0, 211, 255, 1)",
        "name": "Annotations & Alerts",
        "target": {
          "limit": 100,
          "matchAny": false,
          "tags": [],
          "type": "dashboard"
        },
        "type": "dashboard"
      }
    ]
  },
  "editable": true,
  "fiscalYearStartMonth": 0,
  "graphTooltip": 0,
  "links": [],
  "liveNow": false,
  "panels": [
    {
      "fieldConfig": {
        "defaults": {
          "color": {
            "mode": "continuous-RdYlGr"
          },
          "custom": {
            "fillOpacity": 55,
            "lineWidth": 4
          },
          "mappings": [],
          "max": 1,
          "min": 0,
          "thresholds": {
            "mode": "absolute",
            "steps": [
              {
                "color": "green",
                "value": null
              }
            ]
          },
          "unit": "bool_on_off"
        },
        "overrides": []
      },
      "gridPos": {
        "h": 7,
        "w": 8,
        "x": 0,
        "y": 0
      },
      "id": 18,
      "options": {
        "alignValue": "left",
        "legend": {
          "displayMode": "hidden",
          "placement": "bottom"
        },
        "mergeValues": true,
        "rowHeight": 0.9,
        "showValue": "auto",
        "tooltip": {
          "mode": "single"
        }
      },
      "pluginVersion": "8.3.2",
      "targets": [
        {
          "datasource": {
            "type": "prometheus",
            "uid": "promdts1"
          },
          "exemplar": false,
          "expr": "up{job=\"drone\"}",
          "format": "time_series",
          "instant": false,
          "interval": "",
          "intervalFactor": 1,
          "legendFormat": " ",
          "refId": "A"
        }
      ],
      "title": "Health check",
      "type": "state-timeline"
    },
    {
      "fieldConfig": {
        "defaults": {
          "color": {
            "mode": "continuous-BlPu"
          },
          "mappings": [],
          "thresholds": {
            "mode": "absolute",
            "steps": [
              {
                "color": "green",
                "value": null
              }
            ]
          }
        },
        "overrides": []
      },
      "gridPos": {
        "h": 7,
        "w": 8,
        "x": 8,
        "y": 0
      },
      "id": 17,
      "options": {
        "displayMode": "gradient",
        "orientation": "horizontal",
        "reduceOptions": {
          "calcs": [
            "lastNotNull"
          ],
          "fields": "",
          "values": false
        },
        "showUnfilled": true
      },
      "pluginVersion": "8.3.2",
      "targets": [
        {
          "datasource": {
            "type": "prometheus",
            "uid": "promdts1"
          },
          "exemplar": true,
          "expr": "sum(visdrone_model_http_requests_total{job='drone'})by(status) ",
          "interval": "",
          "legendFormat": "",
          "refId": "A"
        }
      ],
      "title": "Request Status count",
      "transformations": [
        {
          "id": "labelsToFields",
          "options": {
            "valueLabel": "status"
          }
        }
      ],
      "type": "bargauge"
    },
    {
      "fieldConfig": {
        "defaults": {
          "color": {
            "mode": "continuous-BlPu"
          },
          "custom": {
            "axisLabel": "",
            "axisPlacement": "auto",
            "barAlignment": 0,
            "drawStyle": "line",
            "fillOpacity": 80,
            "gradientMode": "opacity",
            "hideFrom": {
              "legend": false,
              "tooltip": false,
              "viz": false
            },
            "lineInterpolation": "smooth",
            "lineWidth": 4,
            "pointSize": 5,
            "scaleDistribution": {
              "type": "linear"
            },
            "showPoints": "never",
            "spanNulls": true,
            "stacking": {
              "group": "A",
              "mode": "none"
            },
            "thresholdsStyle": {
              "mode": "off"
            }
          },
          "mappings": [],
          "thresholds": {
            "mode": "absolute",
            "steps": [
              {
                "color": "green",
                "value": null
              },
              {
                "color": "red",
                "value": 80
              }
            ]
          },
          "unit": "short"
        },
        "overrides": []
      },
      "gridPos": {
        "h": 7,
        "w": 8,
        "x": 16,
        "y": 0
      },
      "id": 21,
      "options": {
        "legend": {
          "calcs": [],
          "displayMode": "hidden",
          "placement": "bottom"
        },
        "tooltip": {
          "mode": "single"
        }
      },
      "pluginVersion": "8.3.2",
      "targets": [
        {
          "datasource": {
            "type": "prometheus",
            "uid": "promdts1"
          },
          "exemplar": true,
          "expr": "sum(visdrone_model_http_requests_total)",
          "format": "time_series",
          "interval": "",
          "legendFormat": "",
          "refId": "A"
        }
      ],
      "title": "Requests count",
      "transformations": [
        {
          "id": "labelsToFields",
          "options": {
            "mode": "columns",
            "valueLabel": "handler"
          }
        }
      ],
      "type": "timeseries"
    },
    {
      "description": "Response Time for succeeded Images API",
      "fieldConfig": {
        "defaults": {
          "color": {
            "mode": "continuous-BlYlRd"
          },
          "mappings": [],
          "thresholds": {
            "mode": "absolute",
            "steps": [
              {
                "color": "green",
                "value": null
              },
              {
                "color": "red",
                "value": 80
              }
            ]
          }
        },
        "overrides": []
      },
      "gridPos": {
        "h": 9,
        "w": 9,
        "x": 0,
        "y": 7
      },
      "id": 4,
      "options": {
        "displayMode": "gradient",
        "orientation": "auto",
        "reduceOptions": {
          "calcs": [
            "lastNotNull"
          ],
          "fields": "",
          "values": false
        },
        "showUnfilled": true
      },
      "pluginVersion": "8.3.2",
      "targets": [
        {
          "datasource": {
            "type": "prometheus",
            "uid": "promdts1"
          },
          "exemplar": false,
          "expr": "visdrone_model_http_request_duration_seconds_bucket{handler=\"/predictions/images\", status=\"2xx\"}",
          "format": "heatmap",
          "instant": false,
          "interval": "",
          "intervalFactor": 1,
          "legendFormat": "{{le}}",
          "refId": "A"
        }
      ],
      "title": "Image response time",
      "type": "bargauge"
    },
    {
      "fieldConfig": {
        "defaults": {
          "color": {
            "fixedColor": "dark-blue",
            "mode": "fixed"
          },
          "mappings": [],
          "thresholds": {
            "mode": "absolute",
            "steps": [
              {
                "color": "dark-blue",
                "value": null
              }
            ]
          }
        },
        "overrides": []
      },
      "gridPos": {
        "h": 9,
        "w": 3,
        "x": 9,
        "y": 7
      },
      "id": 11,
      "options": {
        "orientation": "auto",
        "reduceOptions": {
          "calcs": [
            "lastNotNull"
          ],
          "fields": "",
          "values": false
        },
        "showThresholdLabels": false,
        "showThresholdMarkers": true
      },
      "pluginVersion": "8.3.2",
      "targets": [
        {
          "datasource": {
            "type": "prometheus",
            "uid": "promdts1"
          },
          "exemplar": true,
          "expr": "sum(visdrone_model_http_requests_total{handler=\"/predictions/images\"})",
          "interval": "",
          "legendFormat": "",
          "refId": "A"
        }
      ],
      "title": "Images Count",
      "type": "gauge"
    },
    {
      "description": "Response Time for succeeded videos API",
      "fieldConfig": {
        "defaults": {
          "color": {
            "mode": "continuous-BlYlRd"
          },
          "mappings": [],
          "thresholds": {
            "mode": "absolute",
            "steps": [
              {
                "color": "green",
                "value": null
              },
              {
                "color": "red",
                "value": 80
              }
            ]
          },
          "unit": "none"
        },
        "overrides": []
      },
      "gridPos": {
        "h": 9,
        "w": 9,
        "x": 12,
        "y": 7
      },
      "id": 5,
      "options": {
        "displayMode": "gradient",
        "orientation": "auto",
        "reduceOptions": {
          "calcs": [
            "lastNotNull"
          ],
          "fields": "",
          "values": false
        },
        "showUnfilled": true
      },
      "pluginVersion": "8.3.2",
      "targets": [
        {
          "datasource": {
            "type": "prometheus",
            "uid": "promdts1"
          },
          "exemplar": false,
          "expr": "visdrone_model_video_time_bucket{handler=\"/predictions/videos\", status=\"2xx\"}",
          "format": "heatmap",
          "instant": false,
          "interval": "",
          "intervalFactor": 1,
          "legendFormat": "{{le}}",
          "refId": "A"
        }
      ],
      "title": "Video response time",
      "type": "bargauge"
    },
    {
      "fieldConfig": {
        "defaults": {
          "color": {
            "fixedColor": "dark-purple",
            "mode": "fixed"
          },
          "mappings": [],
          "thresholds": {
            "mode": "absolute",
            "steps": [
              {
                "color": "green",
                "value": null
              }
            ]
          }
        },
        "overrides": []
      },
      "gridPos": {
        "h": 9,
        "w": 3,
        "x": 21,
        "y": 7
      },
      "id": 13,
      "options": {
        "orientation": "auto",
        "reduceOptions": {
          "calcs": [
            "lastNotNull"
          ],
          "fields": "",
          "values": false
        },
        "showThresholdLabels": false,
        "showThresholdMarkers": true
      },
      "pluginVersion": "8.3.2",
      "targets": [
        {
          "datasource": {
            "type": "prometheus",
            "uid": "promdts1"
          },
          "exemplar": true,
          "expr": "sum(visdrone_model_http_requests_total{handler=\"/predictions/videos\"})",
          "interval": "",
          "legendFormat": "",
          "refId": "A"
        }
      ],
      "title": "Videos Count",
      "type": "gauge"
    },
    {
      "fieldConfig": {
        "defaults": {
          "color": {
            "mode": "continuous-BlYlRd"
          },
          "mappings": [],
          "thresholds": {
            "mode": "absolute",
            "steps": [
              {
                "color": "blue",
                "value": null
              },
              {
                "color": "red",
                "value": 80
              }
            ]
          }
        },
        "overrides": []
      },
      "gridPos": {
        "h": 8,
        "w": 9,
        "x": 0,
        "y": 16
      },
      "id": 2,
      "options": {
        "displayMode": "gradient",
        "orientation": "auto",
        "reduceOptions": {
          "calcs": [
            "lastNotNull"
          ],
          "fields": "",
          "values": false
        },
        "showUnfilled": true
      },
      "pluginVersion": "8.3.2",
      "targets": [
        {
          "datasource": {
            "type": "prometheus",
            "uid": "promdts1"
          },
          "exemplar": false,
          "expr": "visdrone_model_people_count_bucket",
          "format": "heatmap",
          "interval": "",
          "legendFormat": "{{le}}",
          "refId": "A"
        }
      ],
      "title": "Count Distribution",
      "type": "bargauge"
    },
    {
      "fieldConfig": {
        "defaults": {
          "color": {
            "mode": "palette-classic"
          },
          "custom": {
            "hideFrom": {
              "legend": false,
              "tooltip": false,
              "viz": false
            }
          },
          "mappings": []
        },
        "overrides": []
      },
      "gridPos": {
        "h": 8,
        "w": 3,
        "x": 9,
        "y": 16
      },
      "id": 15,
      "options": {
        "displayLabels": [
          "name",
          "value"
        ],
        "legend": {
          "displayMode": "hidden",
          "placement": "bottom"
        },
        "pieType": "donut",
        "reduceOptions": {
          "calcs": [
            "lastNotNull"
          ],
          "fields": "",
          "values": false
        },
        "tooltip": {
          "mode": "single"
        }
      },
      "targets": [
        {
          "datasource": {
            "type": "prometheus",
            "uid": "promdts1"
          },
          "exemplar": true,
          "expr": "visdrone_model_query_parameter_count_total",
          "interval": "",
          "legendFormat": "",
          "refId": "A"
        }
      ],
      "title": "Query Counting",
      "transformations": [
        {
          "id": "labelsToFields",
          "options": {
            "keepLabels": [
              "query_count"
            ],
            "valueLabel": "query_count"
          }
        }
      ],
      "type": "piechart"
    },
    {
      "fieldConfig": {
        "defaults": {
          "color": {
            "mode": "continuous-BlYlRd"
          },
          "custom": {
            "fillOpacity": 80,
            "gradientMode": "scheme",
            "hideFrom": {
              "legend": false,
              "tooltip": false,
              "viz": false
            },
            "lineWidth": 1
          },
          "mappings": [],
          "thresholds": {
            "mode": "absolute",
            "steps": [
              {
                "color": "green",
                "value": null
              },
              {
                "color": "red",
                "value": 80
              }
            ]
          }
        },
        "overrides": []
      },
      "gridPos": {
        "h": 8,
        "w": 12,
        "x": 12,
        "y": 16
      },
      "id": 23,
      "options": {
        "bucketOffset": 0,
        "combine": false,
        "legend": {
          "calcs": [],
          "displayMode": "hidden",
          "placement": "bottom"
        }
      },
      "targets": [
        {
          "datasource": {
            "type": "prometheus",
            "uid": "promdts1"
          },
          "exemplar": true,
          "expr": "rate(visdrone_model_http_request_size_bytes_count{status=\"2xx\", handler=~\"/predictions/images|/predictions/videos\"}[5m])",
          "interval": "",
          "legendFormat": "",
          "refId": "A"
        }
      ],
      "title": "Request size",
      "transformations": [
        {
          "id": "calculateField",
          "options": {
            "mode": "reduceRow",
            "reduce": {
              "include": [
                "{handler=\"/predictions/images\", instance=\"host.docker.internal:8000\", job=\"drone\", method=\"POST\", status=\"2xx\"}",
                "{handler=\"/predictions/videos\", instance=\"host.docker.internal:8000\", job=\"drone\", method=\"POST\", status=\"2xx\"}"
              ],
              "reducer": "sum"
            },
            "replaceFields": true
          }
        }
      ],
      "type": "histogram"
    }
  ],
  "refresh": false,
  "schemaVersion": 33,
  "style": "dark",
  "tags": [],
  "templating": {
    "list": []
  },
  "time": {
    "from": "now-1h",
    "to": "now"
  },
  "timepicker": {},
  "timezone": "",
  "title": "Visdrone",
  "uid": "RSZtDC27k",
  "version": 1,
  "weekStart": ""
}